bluebild_tools/__init__.py
bluebild_tools/cupy_util.py
bluebild_tools-0.0.3.dist-info/LICENSE
bluebild_tools-0.0.3.dist-info/METADATA
bluebild_tools-0.0.3.dist-info/WHEEL
bluebild_tools-0.0.3.dist-info/top_level.txt
bluebild_tools-0.0.3.dist-info/RECORD
