Metadata-Version: 2.1
Name: bluebild-tools
Version: 0.0.3
Summary: Tools around Bluebild@EPFL
Home-page: https://github.com/epfl-radio-astro/bluebild-tools.git
Author: Etienne Orliac
Author-email: etienne.orliac@epfl.ch
License: UNKNOWN
Platform: UNKNOWN
Classifier: Programming Language :: Python :: 3
Classifier: License :: OSI Approved :: MIT License
Classifier: Operating System :: OS Independent
Requires-Python: >=3.6
License-File: LICENSE
